pyluxafor/__init__.py
pyluxafor/pyluxafor.py
pyluxafor-0.2.0.dist-info/DESCRIPTION.rst
pyluxafor-0.2.0.dist-info/METADATA
pyluxafor-0.2.0.dist-info/RECORD
pyluxafor-0.2.0.dist-info/WHEEL
pyluxafor-0.2.0.dist-info/metadata.json
pyluxafor-0.2.0.dist-info/top_level.txt
