Metadata-Version: 2.0
Name: pyluxafor
Version: 0.2.0
Summary: Python API for the Luxafor Flag
Home-page: https://github.com/takeontom/pyluxafor
Author: Tom Smith
Author-email: tom@takeontom.com
License: MIT license
Keywords: pyluxafor
Platform: UNKNOWN
Classifier: Development Status :: 2 - Pre-Alpha
Classifier: Intended Audience :: Developers
Classifier: License :: OSI Approved :: MIT License
Classifier: Natural Language :: English
Classifier: Programming Language :: Python :: 3.5
Requires-Dist: pyusb (==1.0.0)
